kount_client/__init__.py
kount_client/api_client.py
kount_client/configuration.py
kount_client/rest.py
kount_client/api/__init__.py
kount_client/api/kount_ris_app_api.py
kount_client/api/values_api.py
kount_client/models/__init__.py
kount_client/models/billing_address.py
kount_client/models/cart_item.py
kount_client/models/inquiry_model.py
kount_client/models/kc_event.py
kount_client/models/response_model.py
kount_client/models/shipping_address.py
kount_client/models/user_defined_field.py
test/__init__.py
test/test_billing_address.py
test/test_cart_item.py
test/test_inquiry_model.py
test/test_kc_event.py
test/test_kount_ris_app_api.py
test/test_response_model.py
test/test_shipping_address.py
test/test_user_defined_field.py
test/test_values_api.py
san_swagger_test-1.0.9.dist-info/METADATA
san_swagger_test-1.0.9.dist-info/WHEEL
san_swagger_test-1.0.9.dist-info/top_level.txt
san_swagger_test-1.0.9.dist-info/RECORD
